scrapy_corenlp/__init__.py
scrapy_corenlp/middlewares.py
scrapy_corenlp-0.2.0.dist-info/DESCRIPTION.rst
scrapy_corenlp-0.2.0.dist-info/METADATA
scrapy_corenlp-0.2.0.dist-info/RECORD
scrapy_corenlp-0.2.0.dist-info/WHEEL
scrapy_corenlp-0.2.0.dist-info/metadata.json
scrapy_corenlp-0.2.0.dist-info/top_level.txt
