Metadata-Version: 2.0
Name: scrapy-corenlp
Version: 0.2.0
Summary: Scrapy spider middleware :: Stanford CoreNLP Named Entity Recognition
Home-page: https://github.com/vu3jej/scrapy-corenlp
Author: Jithesh E J
Author-email: mail@jithesh.net
License: BSD-2-Clause
Platform: UNKNOWN
Classifier: Development Status :: 3 - Alpha
Classifier: Programming Language :: Python :: 2.7
Classifier: Programming Language :: Python :: 3.4
Classifier: Programming Language :: Python :: 3.5
Classifier: Topic :: Text Processing :: Linguistic
